serve_rs-0.1.6.dist-info/METADATA
serve_rs-0.1.6.dist-info/WHEEL
serve_rs-0.1.6.dist-info/entry_points.txt
servers/__init__.py
servers/servers.cpython-313-darwin.so
serve_rs-0.1.6.dist-info/RECORD
