Metadata-Version: 2.4
Name: serve-rs
Version: 0.1.6
Classifier: Programming Language :: Rust
Classifier: Programming Language :: Python :: Implementation :: CPython
Classifier: Programming Language :: Python :: Implementation :: PyPy
Summary: Simple, fast gunicorn replacement. Feature parity PR's welcome
Requires-Python: >=3.8
